[
  {
    "name": "theme_info",
    "theme_name": "MISTIQ",
    "theme_version": "1.0.0",
    "theme_author": "MISTIQ",
    "theme_documentation_url": "",
    "theme_support_url": ""
  },
  {
    "name": "Logo",
    "settings": [
      { "type": "image_picker", "id": "logo", "label": "Logo" },
      { "type": "image_picker", "id": "favicon", "label": "Favicon" }
    ]
  },
  {
    "name": "Social media",
    "settings": [
      { "type": "text", "id": "social_instagram", "label": "Instagram", "default": "@shopmistiq" },
      { "type": "text", "id": "social_tiktok", "label": "TikTok", "default": "@shopmistiq" }
    ]
  }
]
